nlmanager/__init__.py
nlmanager/nllistener.py
nlmanager/nlmanager.py
nlmanager/nlpacket.py
nlmanager-1.0.0.dist-info/LICENSE
nlmanager-1.0.0.dist-info/METADATA
nlmanager-1.0.0.dist-info/WHEEL
nlmanager-1.0.0.dist-info/top_level.txt
nlmanager-1.0.0.dist-info/RECORD
