Metadata-Version: 2.1
Name: nlmanager
Version: 1.0.0
Summary: python-nlmanager - Netlink interface using Python
Home-page: https://www.cumulusnetworks.com/
Author: Julien Fortin
Author-email: julien@cumulusnetworks.com
Maintainer: Julien Fortin
Maintainer-email: julien@cumulusnetworks.com
License: GNU General Public License v2
Keywords: python netlink manager nlmanager library
Platform: UNKNOWN
Classifier: Development Status :: 5 - Production/Stable
Classifier: Environment :: Console
Classifier: Intended Audience :: System Administrators
Classifier: License :: OSI Approved :: GNU General Public License v2 (GPLv2)
Classifier: Natural Language :: English
Classifier: Operating System :: POSIX :: Linux
Classifier: Programming Language :: Python :: 2
Classifier: Programming Language :: Python :: 2.7
Classifier: Topic :: System :: Networking
Classifier: Topic :: System :: Systems Administration
Requires-Dist: ipaddr
